jupyterlab_theme_python_courses/__init__.py
jupyterlab_theme_python_courses/_version.py
jupyterlab_theme_python_courses/labextension/package.json
jupyterlab_theme_python_courses/labextension/static/509.756bc5605d43d9f4344b.js
jupyterlab_theme_python_courses/labextension/static/59.11e62886db0e2dc3cc3b.js
jupyterlab_theme_python_courses/labextension/static/remoteEntry.00ccff6c7b8ccfd5fe9e.js
jupyterlab_theme_python_courses/labextension/static/style.js
jupyterlab_theme_python_courses/labextension/static/third-party-licenses.json
jupyterlab_theme_python_courses-0.3.5.data/data/share/jupyter/labextensions/jupyterlab_theme_python_courses/package.json
jupyterlab_theme_python_courses-0.3.5.data/data/share/jupyter/labextensions/jupyterlab_theme_python_courses/static/509.756bc5605d43d9f4344b.js
jupyterlab_theme_python_courses-0.3.5.data/data/share/jupyter/labextensions/jupyterlab_theme_python_courses/static/59.11e62886db0e2dc3cc3b.js
jupyterlab_theme_python_courses-0.3.5.data/data/share/jupyter/labextensions/jupyterlab_theme_python_courses/static/remoteEntry.00ccff6c7b8ccfd5fe9e.js
jupyterlab_theme_python_courses-0.3.5.data/data/share/jupyter/labextensions/jupyterlab_theme_python_courses/static/style.js
jupyterlab_theme_python_courses-0.3.5.data/data/share/jupyter/labextensions/jupyterlab_theme_python_courses/static/third-party-licenses.json
jupyterlab_theme_python_courses-0.3.5.data/data/share/jupyter/labextensions/jupyterlab_theme_python_courses/install.json
jupyterlab_theme_python_courses-0.3.5.dist-info/METADATA
jupyterlab_theme_python_courses-0.3.5.dist-info/WHEEL
jupyterlab_theme_python_courses-0.3.5.dist-info/licenses/LICENSE
jupyterlab_theme_python_courses-0.3.5.dist-info/RECORD
