Metadata-Version: 2.4
Name: jupyterlab_theme_python_courses
Version: 0.3.5
Summary: A JupyterLab extension.
Project-URL: Homepage, https://gitlab.com/uweschmitt/jupyterlab_theme_python_courses
Project-URL: Bug Tracker, https://gitlab.com/uweschmitt/jupyterlab_theme_python_courses/issues
Project-URL: Repository, https://gitlab.com/uweschmitt/jupyterlab_theme_python_courses.git
Author-email: jupyterlab_theme_python_courses <uwe.schmitt@id.ethz.ch>
License: BSD 3-Clause License
License-File: LICENSE
Keywords: jupyter,jupyterlab,jupyterlab-extension
Classifier: Framework :: Jupyter
Classifier: Framework :: Jupyter :: JupyterLab
Classifier: Framework :: Jupyter :: JupyterLab :: 4
Classifier: Framework :: Jupyter :: JupyterLab :: Extensions
Classifier: Framework :: Jupyter :: JupyterLab :: Extensions :: Prebuilt
Classifier: License :: OSI Approved :: BSD License
Classifier: Programming Language :: Python
Classifier: Programming Language :: Python :: 3
Classifier: Programming Language :: Python :: 3.9
Classifier: Programming Language :: Python :: 3.10
Classifier: Programming Language :: Python :: 3.11
Classifier: Programming Language :: Python :: 3.12
Classifier: Programming Language :: Python :: 3.13
Requires-Python: >=3.9
Requires-Dist: jupyter-packaging>=0.12.3
Requires-Dist: jupyter>=1.1.1
Requires-Dist: jupyterlab-server>=2.27.3
